{
  "patch_id": "16AI-QW-38G-R6A-EOS-03A",
  "runner": "orchestrator_local_infer_entry",
  "enforcement_patch": true,
  "audit_only": false,
  "eos_guard_policy": "CONDITIONAL_SUPPRESS_BEFORE_MIN_NEW_TOKENS_RESTORE_AFTER",
  "request_wide_eos_ban_used": false,
  "eos_restore_enabled": true,
  "eos_restore_policy": "ALLOW_EOS_AFTER_MIN_NEW_TOKENS",
  "min_new_tokens_effective_in_sampler": 8,
  "finish_reason_legal": true,
  "checkpoint_modified": false,
  "tokenizer_modified": false,
  "safetensors_modified": false,
  "lm_head_modified": false,
  "final_norm_modified": false,
  "ban_mask_modified": false
}
