{
  "name": "hallucination",
  "decode_session_id": "mock-decode-session-hallucination",
  "cue_id": "mock-cue-0003",
  "candidate_id": "candidate-qe-hallucination",
  "source_en": "Run.",
  "candidate_ko": "지금 당장 경찰서로 달려가서 모든 걸 설명해.",
  "final_gate_receipt_hash": "mock-final-gate-receipt-hash",
  "candidate_quality_receipt_hash": "mock-quality-receipt-hash",
  "expected_decision": "ReviewRecommended",
  "expected_reason": "HallucinationRisk",
  "hallucination_fixture_flag": true,
  "patch_id": "16AI-QW-38G-R6A-DECODE-12",
  "domain_ssot": "en_to_ko_translation_subtitle_machine"
}