{
  "id": "lora_rt02b_f_full_backoff_01",
  "cmd": "run.domain_adapter_backoff",
  "payload": {
    "kind": "infer",
    "input": "지금은 인사말을 자연스럽게 써줘.",
    "task": "freeform",
    "modelSpecPath": ".\\specs\\model_spec_v5_48259.toml",
    "tokenizerManifestPath": ".\\artifacts\\tokenizer_manifest_v5_final.json",
    "checkpointPaths": [
      ".\\tokenizer_v5\\artifacts\\full_model_vocab_v5_resized.safetensors"
    ],
    "maxNewTokens": 48,
    "minNewTokens": 8,
    "seed": 42,
    "temperature": 0.32,
    "topP": 0.90,
    "topK": 40,
    "minP": 0.05,
    "repetitionPenalty": 1.10,
    "domainAdapterEnabled": true,
    "domainAdapterId": "tinyllama_1p1b_v5_guarded_dump_full_gpu_cap192_shared_hidden_head_lora_full",
    "domainAdapterPath": ".\\workspace\\domain_adapters\\tinyllama_1p1b_v5_guarded_dump_full_gpu_cap192_shared_hidden_head_lora.full.safetensors",
    "domainAdapterManifestPath": ".\\workspace\\domain_adapters\\tinyllama_1p1b_v5_guarded_dump_full_gpu_cap192_shared_hidden_head_lora.full.manifest.json",
    "domainAdapterScale": 0.25,
    "domainAdapterNormClampEnabled": true,
    "domainAdapterSafeDeltaRatio": 0.25,
    "domainAdapterWarnDeltaRatio": 0.35,
    "domainAdapterBackoffDeltaRatio": 0.50,
    "domainAdapterHardDisableDeltaRatio": 0.50,
    "domainAdapterBackoffEnabled": true,
    "domainAdapterBackoffScales": [0.25, 0.15, 0.10, 0.05, 0.0],
    "domainAdapterBackoffOnMojibake": true,
    "domainAdapterBackoffOnDeltaRatio": true,
    "domainAdapterMojibakeGuardEnabled": true,
    "domainAdapterBackoffReceiptPath": ".\\workspace\\lora_rt02b_f_backoff_receipt.json",
    "domainAdapterScaleRetryTracePath": ".\\workspace\\lora_rt02b_f_scale_retry_trace.json",
    "domainAdapterMojibakeGuardReceiptPath": ".\\workspace\\lora_rt02b_f_mojibake_guard_receipt.json",
    "memoryBudgetEnabled": true,
    "memoryBudgetReceiptPath": ".\\workspace\\lora_rt02b_f_mem_receipt.json",
    "mem03CacheOwnerAuditEnabled": true,
    "mem03HardPurgeEnabled": true,
    "mem03OwnerAuditReceiptPath": ".\\workspace\\lora_rt02b_f_mem03_owner_receipt.json",
    "mem03HardPurgeReceiptPath": ".\\workspace\\lora_rt02b_f_mem03_purge_receipt.json",
    "mem03CacheOwnerLedgerPath": ".\\workspace\\lora_rt02b_f_mem03_ledger.jsonl",
    "purgeRequestCachesAfterInfer": true,
    "purgeReadbackStagingAfterInfer": true,
    "purgeEmbeddingRowGatherAfterInfer": true,
    "purgeKvCacheAfterInfer": true,
    "purgeDomainAdapterCacheAfterInfer": true,
    "purgeNativeAtlasAfterInfer": true,
    "purgeModelInstanceCacheAfterInfer": false,
    "keepModelLoaded": true,
    "keepGpuPipelineWarm": false,
    "keepFullVocabAtlasWarm": false
  }
}
