{
  "patch_id": "ASH-FT-41",
  "delta_candidate_manifest_created": true,
  "delta_candidate_schema_version": "ash_ft41_selected_group_delta_candidate_v1",
  "candidate_id": "ash_ft41_selected_group_candidate",
  "selected_group_id": "",
  "ft40_receipt_sha256": "",
  "forward_loss_receipt_sha256": "",
  "backward_gradient_receipt_sha256": "",
  "optimizer_candidate_receipt_sha256": "",
  "numeric_safety_receipt_sha256": "",
  "candidate_payload_mode": "descriptor_only",
  "candidate_payload_written": false,
  "official_delta_packet_created": false,
  "delta_stack_appended": false,
  "manifest_status": "PASS"
}
