{
  "patch_id": "16AI-QW-38G-R6A-WCTX-21",
  "domain_ssot": "en_to_ko_translation_subtitle_machine",
  "schema_version": 1,
  "cases": [
    {
      "case_id": "wctx21_empty_ledger_audit_packet_export",
      "pass": true,
      "failure_reasons": [],
      "first_receipt_key": "sha256:651559cd58938020c8fe58bb57d7bd722419fb9bf9a18b49e5ac8e2e90727127",
      "second_receipt_key": "sha256:651559cd58938020c8fe58bb57d7bd722419fb9bf9a18b49e5ac8e2e90727127",
      "deterministic": true,
      "export_status": "exported_empty_ledger",
      "export_format": "json_and_markdown_audit_packet",
      "audit_packet_created": true,
      "empty_ledger_packet": true,
      "source_query_receipt_count": 4,
      "section_count": 7,
      "total_revision_events_seen": 0,
      "total_commit_events_seen": 0,
      "total_revert_events_seen": 0,
      "ledger_mutated": false,
      "revision_event_created": false,
      "target_text_mutated": false,
      "runtime_default_apply": false,
      "risk_pass": true
    }
  ],
  "summary": {
    "patch_id": "16AI-QW-38G-R6A-WCTX-21",
    "domain_ssot": "en_to_ko_translation_subtitle_machine",
    "total_cases": 1,
    "pass_cases": 1,
    "fail_cases": 0,
    "deterministic_failures": 0,
    "risk_failures": 0,
    "exported_count": 0,
    "exported_empty_ledger_count": 1,
    "blocked_missing_query_receipt_count": 0,
    "blocked_inconsistent_query_set_count": 0,
    "audit_packet_created_count": 1,
    "empty_ledger_packet_count": 1,
    "total_sections_created": 7,
    "total_revision_events_seen": 0,
    "total_commit_events_seen": 0,
    "total_revert_events_seen": 0,
    "ledger_mutation_count": 0,
    "revision_event_created_count": 0,
    "target_text_mutation_count": 0,
    "commit_executed_in_export_count": 0,
    "rollback_executed_in_export_count": 0,
    "runtime_default_apply_count": 0,
    "runtime_apply_gate_open_count": 0,
    "rerank_applied_count": 0,
    "decode_executed_in_export_count": 0,
    "generation_executed_in_export_count": 0,
    "model_forward_executed_in_export_count": 0,
    "sampling_executed_in_export_count": 0
  }
}